first_tpl/__init__.py
first_tpl/simple_add.py
first_tpl-0.0.1.dist-info/LICENSE
first_tpl-0.0.1.dist-info/METADATA
first_tpl-0.0.1.dist-info/WHEEL
first_tpl-0.0.1.dist-info/top_level.txt
first_tpl-0.0.1.dist-info/RECORD
