Metadata-Version: 2.1
Name: first-tpl
Version: 0.0.1
Summary: first trial
Author: Dubem
Author-email: michaeligbomezie@gmail.com
Classifier: Programming Language :: Python :: 3
Classifier: License :: OSI Approved :: MIT License
Classifier: Operating System :: OS Independent
License-File: LICENSE
